[
  {
    "color": "#7057ff",
    "name": "good first issue"
  },
  {
    "color": "#008672",
    "name": "help wanted"
  },
  {
    "color": "#e4e669",
    "name": "invalid"
  },
  {
    "color": "#e11d21",
    "name": "priority:critical"
  },
  {
    "color": "#eb6420",
    "name": "priority:high"
  },
  {
    "color": "#009800",
    "name": "priority:low"
  },
  {
    "color": "#fbca04",
    "name": "priority:medium"
  },
  {
    "color": "#000000",
    "name": "status:abandoned"
  },
  {
    "color": "#009800",
    "name": "status:accepted"
  },
  {
    "color": "#bfe5bf",
    "name": "status:available"
  },
  {
    "color": "#e11d21",
    "name": "status:blocked"
  },
  {
    "color": "#006b75",
    "name": "status:completed"
  },
  {
    "color": "#cccccc",
    "name": "status:in_progress"
  },
  {
    "color": "#e11d21",
    "name": "status:on_hold"
  },
  {
    "color": "#fef2c0",
    "name": "status:pending"
  },
  {
    "color": "#fbca04",
    "name": "status:review_needed"
  },
  {
    "color": "#e11d21",
    "name": "status:revision_needed"
  },
  {
    "color": "#d73a4a",
    "name": "bug"
  },
  {
    "color": "#0075ca",
    "name": "documentation"
  },
  {
    "color": "#cfd3d7",
    "name": "duplicate"
  },
  {
    "color": "#84b6eb",
    "name": "feature"
  },
  {
    "color": "#fbca04",
    "name": "maintenance"
  },
  {
    "color": "#cc317c",
    "name": "question"
  },
  {
    "color": "#ffffff",
    "name": "wontfix"
  }
]
